scripts/bump_version.py
find_404/cli.py
find_404/crawler.py
find_404-1.3.0.dist-info/METADATA
find_404-1.3.0.dist-info/WHEEL
find_404-1.3.0.dist-info/entry_points.txt
find_404-1.3.0.dist-info/RECORD
