Metadata-Version: 2.4
Name: find_404
Version: 1.3.0
Summary: A tool to find broken links (404s) and oversized pages in websites
Project-URL: Homepage, https://github.com/singiamtel/404-finder
Project-URL: Bug Tracker, https://github.com/singiamtel/404-finder/issues
Author-email: Sergio Garcia <sergio@garciadelacruz.es>
Classifier: License :: OSI Approved :: MIT License
Classifier: Operating System :: OS Independent
Classifier: Programming Language :: Python :: 3
Requires-Python: >=3.7
Requires-Dist: beautifulsoup4>=4.9.0
Requires-Dist: certifi
Requires-Dist: requests>=2.25.0
